{
  "meta": {
    "source": "bol.pt",
    "count": 1
  },
  "shows": [
    {
      "id": "bol-166815",
      "title": "EVITA",
      "type": "limited",
      "venue": "Capitólio",
      "city": "Lisboa",
      "country": "Portugal",
      "lat": 38.7188762,
      "lng": -9.146637,
      "start_date": "2026-06-17",
      "end_date": "2026-06-28",
      "ticket_url": "https://www.bol.pt/Comprar/Bilhetes/166815-evita-capitolio/",
      "image": "https://bolimg.blob.core.windows.net/producao/imagens/espectaculos/cartaz143318.jpg?v=13",
      "tour_name": null,
      "verified": true,
      "source": "bol.pt"
    }
  ]
}